{
    "id_match": "67f16c9e8d133530231b7d3f",
    "firstTurn": 1,
    "type": 1,
    "id": "67f16c9e8d133530231b7d3f",
    "scoreOne": 6,
    "scoreTwo": 14,
    "armyOne": "DL",
    "armyTwo": "DL",
    "armyListOne": {
        "units": [
            {
                "name": "Courtesan of Cibaresh",
                "cost": 705,
                "options": [
                    "Wizard Apprentice",
                    "Divination",
                    "Foresight",
                    "Trampling Hooves",
                    "Kaleidoscopic Flesh"
                ],
                "index": 0,
                "category": "Characters"
            },
            {
                "name": "Omen of Savar",
                "cost": 490,
                "options": [
                    "Battleline Hero",
                    "General",
                    "Wizard Apprentice",
                    "Divination",
                    "Foresight",
                    "Hammer Hand",
                    "Bronze Backbone",
                    "Guiding Bronze Backbone"
                ],
                "index": 0,
                "category": "Characters"
            },
            {
                "name": "Kuulima's Deceiver",
                "cost": 400,
                "options": [
                    "Hammer Hand",
                    "Smite the Unbeliever",
                    "Protean Magic [2]",
                    "Whispers of the Veil"
                ],
                "index": 0,
                "category": "Characters"
            },
            {
                "name": "Succubi",
                "cost": 522,
                "options": [
                    "Torporous Tendrils",
                    "Standard Bearer",
                    "Musician"
                ],
                "index": 0,
                "models": 22,
                "category": "Core"
            },
            {
                "name": "Myrmidons",
                "cost": 480,
                "options": [
                    "Standard Bearer",
                    "Musician",
                    "Unhinging Jaw"
                ],
                "index": 0,
                "models": 22,
                "category": "Core"
            },
            {
                "name": "Brazen Beasts",
                "cost": 520,
                "options": [
                    "Standard Bearer",
                    "Musician",
                    "Whipcrack Tail"
                ],
                "index": 0,
                "models": 4,
                "category": "Special"
            },
            {
                "name": "Blazing Glory",
                "cost": 375,
                "options": [
                    "Horns of Hubris",
                    "Fly"
                ],
                "index": 0,
                "category": "Special"
            },
            {
                "name": "Hellhounds",
                "cost": 324,
                "options": [
                    "Digestive Vomit"
                ],
                "index": 0,
                "models": 12,
                "category": "Special"
            },
            {
                "name": "Threshing Engine",
                "cost": 180,
                "options": [
                    "Standard Bearer",
                    "Fly"
                ],
                "index": 0,
                "models": 1,
                "category": "Special"
            }
        ],
        "pointsPerCategory": {
            "Characters": 1595,
            "Core": 1002,
            "Special": 1399,
            "Total": 3996
        }
    },
    "armyListTwo": {
        "units": [
            {
                "name": "Miser of Sugulag",
                "cost": 860,
                "options": [
                    "Recruiting Officer",
                    "General",
                    "Wizard Master",
                    "Evocation",
                    "Whispers of the Veil",
                    "Chorus of the Damned",
                    "Touch of the Reaper",
                    "Spectral Blades",
                    "Soul Blight",
                    "Mirrored Scales",
                    "Segmented Shell"
                ],
                "index": 0,
                "category": "Characters"
            },
            {
                "name": "Maw of Akaan",
                "cost": 730,
                "options": [
                    "Evocation",
                    "Whispers of the Veil",
                    "Hammer Hand",
                    "Mirrored Scales",
                    "Wizard Apprentice"
                ],
                "index": 0,
                "category": "Characters"
            },
            {
                "name": "Lemures",
                "cost": 350,
                "options": [
                    "Unnatural Roots",
                    "Standard Bearer"
                ],
                "index": 0,
                "models": 15,
                "category": "Core"
            },
            {
                "name": "Lemures",
                "cost": 350,
                "options": [
                    "Unnatural Roots",
                    "Standard Bearer"
                ],
                "index": 1,
                "models": 15,
                "category": "Core"
            },
            {
                "name": "Lemures",
                "cost": 350,
                "options": [
                    "Unnatural Roots",
                    "Standard Bearer"
                ],
                "index": 2,
                "models": 15,
                "category": "Core"
            },
            {
                "name": "Hoarders",
                "cost": 729,
                "options": [
                    "Mirrored Scales",
                    "Smothering Coils",
                    "Standard Bearer",
                    "Fresh Meat",
                    "Favoured of Greed"
                ],
                "index": 0,
                "models": 6,
                "category": "Special"
            },
            {
                "name": "Threshing Engine",
                "cost": 375,
                "options": [
                    "Standard Bearer",
                    "Legion Thresher",
                    "Whipcrack Tail"
                ],
                "index": 0,
                "models": 1,
                "category": "Special"
            },
            {
                "name": "Hellhounds",
                "cost": 249,
                "options": [
                    "Hot Blood"
                ],
                "index": 0,
                "models": 9,
                "category": "Special"
            }
        ],
        "pointsPerCategory": {
            "Characters": 1590,
            "Core": 1050,
            "Special": 1353,
            "Total": 3993
        }
    }
}