{
    "id_match": "682107db09f2b36aaef2d817",
    "firstTurn": 0,
    "type": 1,
    "id": "682107db09f2b36aaef2d817",
    "scoreOne": 11,
    "scoreTwo": 9,
    "armyOne": "WDG",
    "armyTwo": "OnG",
    "armyListOne": {
        "units": [
            {
                "name": "Chosen Lord",
                "cost": 830,
                "options": [
                    "General",
                    "Recruiting Officer",
                    "Wasteland Dragon",
                    "Trophy Rack",
                    "Paired Weapons",
                    "Touch of Greatness",
                    "Immortal Gauntlets",
                    "Wyrd Stone",
                    "Lust",
                    "Dark Prelate"
                ],
                "index": 0,
                "category": "Characters"
            },
            {
                "name": "Sorcerer",
                "cost": 530,
                "options": [
                    "Curse of Lycanthropy",
                    "Light Troops",
                    "Talisman of the Void",
                    "Whispers of the Veil",
                    "Danse Macabre",
                    "Wizard Master",
                    "Evocation",
                    "Chorus of the Damned",
                    "Touch of the Reaper",
                    "Spectral Blades"
                ],
                "index": 0,
                "category": "Characters"
            },
            {
                "name": "Warriors",
                "cost": 570,
                "options": [
                    "Zealots' Banner",
                    "Paired Weapons",
                    "Standard Bearer"
                ],
                "index": 0,
                "models": 25,
                "category": "Core"
            },
            {
                "name": "Warhounds",
                "cost": 130,
                "options": [],
                "index": 0,
                "models": 8,
                "category": "Core"
            },
            {
                "name": "Chosen Knights",
                "cost": 510,
                "options": [
                    "Pride",
                    "Standard Bearer"
                ],
                "index": 0,
                "models": 4,
                "category": "Special"
            },
            {
                "name": "Forsworn",
                "cost": 490,
                "options": [
                    "Great Weapon",
                    "Standard Bearer",
                    "Damnation"
                ],
                "index": 0,
                "models": 6,
                "category": "Special"
            },
            {
                "name": "Warrior Chariot",
                "cost": 220,
                "options": [
                    "Lust"
                ],
                "index": 0,
                "category": "Special"
            },
            {
                "name": "Warrior Chariot",
                "cost": 220,
                "options": [
                    "Lust"
                ],
                "index": 1,
                "category": "Special"
            }
        ],
        "pointsPerCategory": {
            "Characters": 1360,
            "Core": 875,
            "Special": 1440,
            "Total": 3500
        }
    },
    "armyListTwo": {
        "units": [
            {
                "name": "Goblin Witch",
                "cost": 495,
                "options": [
                    "Beastie",
                    "Wizard Master",
                    "Pyromancy",
                    "Fireball",
                    "Flaming Swords",
                    "Pyroclastic Flow",
                    "Pillars of Fire",
                    "Cage of Embers",
                    "Talisman of the Void"
                ],
                "index": 0,
                "category": "Characters"
            },
            {
                "name": "Goblin Demagogue",
                "cost": 190,
                "options": [
                    "Light Troops",
                    "Battle Standard Bearer",
                    "Goga Cauldron",
                    "Shield",
                    "Wild Warding",
                    "Poisoned Spear"
                ],
                "index": 0,
                "category": "Characters"
            },
            {
                "name": "Goblin Demagogue",
                "cost": 170,
                "options": [
                    "General",
                    "Light Troops",
                    "Tazrek's Guard",
                    "Mask of Mindless Violence",
                    "Darrmu and Goblin Gardens",
                    "Great Weapon"
                ],
                "index": 1,
                "category": "Characters"
            },
            {
                "name": "Mad Git",
                "cost": 55,
                "options": [],
                "index": 0,
                "category": "Characters"
            },
            {
                "name": "Mad Git",
                "cost": 55,
                "options": [],
                "index": 1,
                "category": "Characters"
            },
            {
                "name": "Gogtuk Initiate",
                "cost": 50,
                "options": [
                    "Light Troops",
                    "Mauler"
                ],
                "index": 0,
                "category": "Characters"
            },
            {
                "name": "Gogtuk Initiate",
                "cost": 50,
                "options": [
                    "Light Troops",
                    "Mauler"
                ],
                "index": 1,
                "category": "Characters"
            },
            {
                "name": "Gogtuk Initiate",
                "cost": 50,
                "options": [
                    "Light Troops",
                    "Mauler"
                ],
                "index": 2,
                "category": "Characters"
            },
            {
                "name": "Gogtuk Initiate",
                "cost": 50,
                "options": [
                    "Light Troops",
                    "Mauler"
                ],
                "index": 3,
                "category": "Characters"
            },
            {
                "name": "Gogtuk Initiate",
                "cost": 45,
                "options": [
                    "Light Troops",
                    "Netter"
                ],
                "index": 4,
                "category": "Characters"
            },
            {
                "name": "Goblin Rabble",
                "cost": 464,
                "options": [
                    "Goga Cauldron",
                    "Bow",
                    "Poisoned Spear and Shield",
                    "Standard Bearer"
                ],
                "index": 0,
                "models": 48,
                "category": "Core"
            },
            {
                "name": "Goblin Rabble",
                "cost": 409,
                "options": [
                    "Flaming Standard",
                    "Poisoned Spear and Shield",
                    "Standard Bearer"
                ],
                "index": 1,
                "models": 47,
                "category": "Core"
            },
            {
                "name": "Goblin Reavers",
                "cost": 176,
                "options": [
                    "Bow and Spies"
                ],
                "index": 0,
                "models": 8,
                "category": "Core"
            },
            {
                "name": "Gogtuk Neophytes",
                "cost": 220,
                "options": [
                    "Standard Bearer"
                ],
                "index": 0,
                "models": 16,
                "category": "Special"
            },
            {
                "name": "Goblin Artillery",
                "cost": 170,
                "options": [
                    "Git Launcher"
                ],
                "index": 0,
                "category": "Special"
            },
            {
                "name": "Goblin Artillery",
                "cost": 170,
                "options": [
                    "Git Launcher"
                ],
                "index": 1,
                "category": "Special"
            },
            {
                "name": "Goblin Artillery",
                "cost": 90,
                "options": [
                    "Skewerer"
                ],
                "index": 2,
                "category": "Special"
            },
            {
                "name": "Goblin Artillery",
                "cost": 90,
                "options": [
                    "Skewerer"
                ],
                "index": 3,
                "category": "Special"
            },
            {
                "name": "Gnasher Dashers",
                "cost": 150,
                "options": [],
                "index": 0,
                "models": 10,
                "category": "Special"
            },
            {
                "name": "Gnasher Dashers",
                "cost": 150,
                "options": [],
                "index": 1,
                "models": 10,
                "category": "Special"
            },
            {
                "name": "Wrecking Team",
                "cost": 100,
                "options": [],
                "index": 0,
                "category": "Special"
            },
            {
                "name": "Wrecking Team",
                "cost": 100,
                "options": [],
                "index": 1,
                "category": "Special"
            }
        ],
        "pointsPerCategory": {
            "Characters": 1210,
            "Core": 1049,
            "Special": 1240,
            "Total": 3499
        }
    }
}